femtoapi/FemtoAPI.dll
femtoapi/PyFemtoAPI.pyd
femtoapi/__init__.py
femtoapi/shiboken2.abi3.dll
femtoapi-1.0.1.dist-info/METADATA
femtoapi-1.0.1.dist-info/WHEEL
femtoapi-1.0.1.dist-info/top_level.txt
femtoapi-1.0.1.dist-info/RECORD
